{"state":"AL","stateName":"Alabama","county":"Baldwin","fips":"01003","totalAmount":57204724.69,"totalPayments":10926,"yearly":[{"year":2017,"amount":6945624,"payments":1618},{"year":2018,"amount":3746491.45,"payments":1241},{"year":2019,"amount":9291272.74,"payments":1564},{"year":2020,"amount":13230109.86,"payments":2063},{"year":2021,"amount":11225639.2,"payments":1471},{"year":2022,"amount":3872321.71,"payments":888},{"year":2023,"amount":787828.53,"payments":234},{"year":2024,"amount":781521.92,"payments":249},{"year":2025,"amount":7323915.28,"payments":1598}]}