{"state":"KS","stateName":"Kansas","county":"Butler","fips":"01013","totalAmount":100511069.2,"totalPayments":27220,"yearly":[{"year":2017,"amount":3441030,"payments":2506},{"year":2018,"amount":5038483,"payments":3277},{"year":2019,"amount":14781954.27,"payments":4600},{"year":2020,"amount":31539951.1,"payments":5487},{"year":2021,"amount":8507007.48,"payments":2807},{"year":2022,"amount":3975311.31,"payments":356},{"year":2023,"amount":8967506.25,"payments":2198},{"year":2024,"amount":6085239.11,"payments":2568},{"year":2025,"amount":18174586.68,"payments":3421}]}