{"state":"AL","stateName":"Alabama","county":"Covington","fips":"01039","totalAmount":46608096.16,"totalPayments":12963,"yearly":[{"year":2017,"amount":5566056.25,"payments":1795},{"year":2018,"amount":3131383.33,"payments":1229},{"year":2019,"amount":7515302.8,"payments":1806},{"year":2020,"amount":12050170.51,"payments":3214},{"year":2021,"amount":7080700.84,"payments":1799},{"year":2022,"amount":3700478.16,"payments":937},{"year":2023,"amount":614370.66,"payments":288},{"year":2024,"amount":1872150.75,"payments":575},{"year":2025,"amount":5077482.86,"payments":1320}]}