{"state":"CA","stateName":"California","county":"Los Angeles","fips":"06037","totalAmount":11477883.16,"totalPayments":618,"yearly":[{"year":2017,"amount":236545,"payments":47},{"year":2018,"amount":233031.92,"payments":28},{"year":2019,"amount":501136.79,"payments":66},{"year":2020,"amount":4201869.03,"payments":112},{"year":2021,"amount":2901717.54,"payments":96},{"year":2022,"amount":399394.85,"payments":48},{"year":2023,"amount":525607.7,"payments":52},{"year":2024,"amount":182294.81,"payments":70},{"year":2025,"amount":2296285.52,"payments":99}]}