{"state":"CA","stateName":"California","county":"Solano","fips":"06095","totalAmount":57355505.17,"totalPayments":4166,"yearly":[{"year":2017,"amount":3329974.81,"payments":541},{"year":2018,"amount":2604754,"payments":539},{"year":2019,"amount":2122175.13,"payments":636},{"year":2020,"amount":20581241.71,"payments":870},{"year":2021,"amount":5828345.94,"payments":537},{"year":2022,"amount":5486442.16,"payments":227},{"year":2023,"amount":7171939.42,"payments":263},{"year":2024,"amount":3823131.21,"payments":238},{"year":2025,"amount":6407500.79,"payments":315}]}