{"state":"CO","stateName":"Colorado","county":"Alamosa","fips":"08003","totalAmount":28193027.14,"totalPayments":1991,"yearly":[{"year":2017,"amount":897355,"payments":99},{"year":2018,"amount":1282204,"payments":154},{"year":2019,"amount":1131574.65,"payments":149},{"year":2020,"amount":11040196.58,"payments":454},{"year":2021,"amount":3434433.5,"payments":412},{"year":2022,"amount":4795613.33,"payments":226},{"year":2023,"amount":1287656.45,"payments":143},{"year":2024,"amount":912106.56,"payments":171},{"year":2025,"amount":3411887.07,"payments":183}]}