{"state":"MT","stateName":"Montana","county":"Phillips","fips":"08095","totalAmount":120115937.86,"totalPayments":13636,"yearly":[{"year":2017,"amount":11212330.8,"payments":1127},{"year":2018,"amount":8172831,"payments":1186},{"year":2019,"amount":8772093.29,"payments":1342},{"year":2020,"amount":20916884.11,"payments":2497},{"year":2021,"amount":14327066.62,"payments":1674},{"year":2022,"amount":26316272.35,"payments":1526},{"year":2023,"amount":13312428.17,"payments":1731},{"year":2024,"amount":3823069.45,"payments":1162},{"year":2025,"amount":13262962.07,"payments":1391}]}