{"state":"IL","stateName":"Illinois","county":"Effingham","fips":"17049","totalAmount":102133661.78,"totalPayments":49772,"yearly":[{"year":2017,"amount":8622751,"payments":5181},{"year":2018,"amount":13700573,"payments":4325},{"year":2019,"amount":16214010.26,"payments":5240},{"year":2020,"amount":27593632.91,"payments":13602},{"year":2021,"amount":8475901.33,"payments":5744},{"year":2022,"amount":3488193.3,"payments":2208},{"year":2023,"amount":4993478.29,"payments":2672},{"year":2024,"amount":2989021.34,"payments":2114},{"year":2025,"amount":16056100.35,"payments":8686}]}