{"state":"IL","stateName":"Illinois","county":"Peoria","fips":"17143","totalAmount":65978629.36,"totalPayments":25251,"yearly":[{"year":2017,"amount":1963467,"payments":3354},{"year":2018,"amount":7416417,"payments":2048},{"year":2019,"amount":14372213.74,"payments":2658},{"year":2020,"amount":18670680.71,"payments":8870},{"year":2021,"amount":7297458.7,"payments":2816},{"year":2022,"amount":3049351.03,"payments":975},{"year":2023,"amount":1840281.09,"payments":946},{"year":2024,"amount":1551819.3,"payments":979},{"year":2025,"amount":9816940.79,"payments":2605}]}