{"state":"IA","stateName":"Iowa","county":"Kossuth","fips":"19109","totalAmount":270390695.3,"totalPayments":49336,"yearly":[{"year":2017,"amount":14290909,"payments":6188},{"year":2018,"amount":22168963,"payments":3728},{"year":2019,"amount":39882621.4,"payments":4949},{"year":2020,"amount":60815507.53,"payments":12504},{"year":2021,"amount":23386517.27,"payments":4153},{"year":2022,"amount":13617675.35,"payments":2511},{"year":2023,"amount":11960312.08,"payments":2870},{"year":2024,"amount":8464738.33,"payments":2451},{"year":2025,"amount":75803451.34,"payments":9982}]}