{"state":"MN","stateName":"Minnesota","county":"Kittson","fips":"27069","totalAmount":111387402.61,"totalPayments":23971,"yearly":[{"year":2017,"amount":11020090.71,"payments":3215},{"year":2018,"amount":9713412.75,"payments":2438},{"year":2019,"amount":16299197.38,"payments":3512},{"year":2020,"amount":26996603.36,"payments":5929},{"year":2022,"amount":21733544.35,"payments":2242},{"year":2023,"amount":5606672.52,"payments":2002},{"year":2024,"amount":5575740.38,"payments":2183},{"year":2025,"amount":14442141.16,"payments":2450}]}