{"state":"MO","stateName":"Missouri","county":"Pike","fips":"29163","totalAmount":56869659.76,"totalPayments":17310,"yearly":[{"year":2017,"amount":2256931,"payments":1563},{"year":2018,"amount":2772905,"payments":1058},{"year":2019,"amount":12200294.9,"payments":3476},{"year":2020,"amount":14368668.52,"payments":4239},{"year":2021,"amount":5117647.11,"payments":2282},{"year":2022,"amount":3655127.07,"payments":460},{"year":2023,"amount":2262916.85,"payments":622},{"year":2024,"amount":1984921.48,"payments":647},{"year":2025,"amount":12250247.83,"payments":2963}]}