{"state":"NY","stateName":"New York","county":"Greene","fips":"36039","totalAmount":3953284.55,"totalPayments":664,"yearly":[{"year":2017,"amount":402300,"payments":84},{"year":2018,"amount":419946,"payments":90},{"year":2019,"amount":290209.7,"payments":87},{"year":2020,"amount":876093.95,"payments":134},{"year":2021,"amount":632639.76,"payments":104},{"year":2022,"amount":467788.46,"payments":29},{"year":2023,"amount":362497.25,"payments":73},{"year":2024,"amount":57118.45,"payments":16},{"year":2025,"amount":444690.98,"payments":47}]}