{"state":"NC","stateName":"North Carolina","county":"Columbus","fips":"37047","totalAmount":47456141.51,"totalPayments":29256,"yearly":[{"year":2017,"amount":3656547.98,"payments":4332},{"year":2018,"amount":1610191,"payments":2236},{"year":2019,"amount":8317477,"payments":4326},{"year":2020,"amount":10226956.26,"payments":6299},{"year":2021,"amount":6338365.02,"payments":5050},{"year":2022,"amount":5889586.45,"payments":1443},{"year":2023,"amount":639037.69,"payments":313},{"year":2024,"amount":709701.47,"payments":452},{"year":2025,"amount":10068278.64,"payments":4805}]}