{"state":"ND","stateName":"North Dakota","county":"Traill","fips":"38097","totalAmount":165611640.33,"totalPayments":18445,"yearly":[{"year":2017,"amount":3655212,"payments":1275},{"year":2018,"amount":11932339,"payments":1304},{"year":2019,"amount":23894211.17,"payments":2291},{"year":2020,"amount":33458834.46,"payments":4822},{"year":2021,"amount":22373458.63,"payments":2978},{"year":2022,"amount":35200039.62,"payments":1404},{"year":2023,"amount":4690283.21,"payments":1048},{"year":2024,"amount":4450681.32,"payments":1338},{"year":2025,"amount":25956580.92,"payments":1985}]}