{"state":"ND","stateName":"North Dakota","county":"Steele","fips":"38091","totalAmount":126733595.45,"totalPayments":19213,"yearly":[{"year":2017,"amount":3318568,"payments":1557},{"year":2018,"amount":6983254,"payments":1996},{"year":2019,"amount":21087694.47,"payments":2387},{"year":2020,"amount":26001620.97,"payments":4493},{"year":2021,"amount":18011192.25,"payments":3036},{"year":2022,"amount":23369222.48,"payments":1464},{"year":2023,"amount":3874905.74,"payments":1061},{"year":2024,"amount":5180577.13,"payments":1485},{"year":2025,"amount":18906560.41,"payments":1734}]}