{"state":"OH","stateName":"Ohio","county":"Monroe","fips":"39111","totalAmount":4214194.16,"totalPayments":1352,"yearly":[{"year":2017,"amount":15595,"payments":16},{"year":2018,"amount":59513,"payments":49},{"year":2019,"amount":64517.5,"payments":40},{"year":2020,"amount":1159130.57,"payments":375},{"year":2021,"amount":415822.07,"payments":217},{"year":2022,"amount":18824.87,"payments":19},{"year":2023,"amount":228448.49,"payments":61},{"year":2024,"amount":1154443.23,"payments":213},{"year":2025,"amount":1097899.43,"payments":362}]}