{"state":"OH","stateName":"Ohio","county":"Williams","fips":"39171","totalAmount":6666220.38,"totalPayments":2838,"yearly":[{"year":2017,"amount":98584,"payments":49},{"year":2018,"amount":72880,"payments":56},{"year":2019,"amount":71586.18,"payments":60},{"year":2020,"amount":97094.54,"payments":70},{"year":2021,"amount":10195.3,"payments":7},{"year":2022,"amount":3469067.62,"payments":940},{"year":2023,"amount":1464367.99,"payments":727},{"year":2024,"amount":1266147.13,"payments":866},{"year":2025,"amount":116297.62,"payments":63}]}