{"state":"OR","stateName":"Oregon","county":"Malheur","fips":"41045","totalAmount":97794875.28,"totalPayments":11486,"yearly":[{"year":2017,"amount":5599960.69,"payments":1055},{"year":2018,"amount":4576000.98,"payments":1051},{"year":2019,"amount":5155021.55,"payments":1449},{"year":2020,"amount":35929271.16,"payments":2895},{"year":2021,"amount":10342455.55,"payments":1774},{"year":2022,"amount":12318815.66,"payments":863},{"year":2023,"amount":9873001.64,"payments":951},{"year":2024,"amount":2412895.14,"payments":518},{"year":2025,"amount":11587452.91,"payments":930}]}