{"state":"TN","stateName":"Tennessee","county":"Meigs","fips":"47121","totalAmount":4348385.09,"totalPayments":2136,"yearly":[{"year":2017,"amount":500364,"payments":225},{"year":2018,"amount":71706,"payments":84},{"year":2019,"amount":332526.54,"payments":140},{"year":2020,"amount":1226514.16,"payments":707},{"year":2021,"amount":405098.36,"payments":229},{"year":2022,"amount":33644.93,"payments":24},{"year":2023,"amount":492176.57,"payments":142},{"year":2024,"amount":601852.35,"payments":197},{"year":2025,"amount":684502.18,"payments":388}]}