{"state":"UT","stateName":"Utah","county":"Beaver","fips":"49001","totalAmount":18125733.19,"totalPayments":2428,"yearly":[{"year":2017,"amount":247414,"payments":98},{"year":2018,"amount":990103,"payments":156},{"year":2019,"amount":454865.73,"payments":132},{"year":2020,"amount":5215198.36,"payments":531},{"year":2021,"amount":3631644.51,"payments":424},{"year":2022,"amount":2953439.86,"payments":251},{"year":2023,"amount":2692456.65,"payments":381},{"year":2024,"amount":109240.28,"payments":123},{"year":2025,"amount":1831370.8,"payments":332}]}