{"state":"VA","stateName":"Virginia","county":"Campbell, Lynchburg City","fips":"51031","totalAmount":9981461.18,"totalPayments":3412,"yearly":[{"year":2017,"amount":202600,"payments":260},{"year":2018,"amount":359280,"payments":269},{"year":2019,"amount":674812.67,"payments":320},{"year":2020,"amount":3345357.83,"payments":1103},{"year":2021,"amount":1293445.52,"payments":512},{"year":2022,"amount":1089904.16,"payments":250},{"year":2023,"amount":932588.45,"payments":186},{"year":2024,"amount":474519.95,"payments":124},{"year":2025,"amount":1608952.6,"payments":388}]}