{"slug":"4-way-production-inc-greensburg-in","name":"4-WAY PRODUCTION INC","state":"IN","city":"GREENSBURG","totalAmount":1692742.13,"totalPayments":76,"yearly":[],"topPrograms":[{"program":"CFAPCCA2","amount":495492.13},{"program":"CFAPCCCCA","amount":335435.81},{"program":"TMP/MFP 2019 LIVESTOCK","amount":210573},{"program":"TMP/MFP 2019 NON SPECIALTY CROPS","amount":174268.48},{"program":"CFAPCARES","amount":164564.19},{"program":"AGRICULTURAL RISK COVERAGE PROG - COUNTY","amount":128031},{"program":"MARKET FACILITATION PROGRAM - CROPS","amount":125000},{"program":"WHIP PLUS 3 ASSISTANCE","amount":28222.52},{"program":"PRICE LOSS COVERAGE PROGRAM","amount":25167},{"program":"CRP PAYMENT - ANNUAL RENTAL","amount":5988}]}