{"slug":"agrifund-llc-rayville-la","name":"Agrifund LLC","state":"LA","city":"RAYVILLE","totalAmount":9588827.77,"totalPayments":929,"yearly":[{"year":2018,"amount":8310323.87,"payments":834,"programs":{"AGRICULTURAL RISK COVERAGE PROG - COUNTY":481075,"MARKET FACILITATION PROGRAM - CROPS":5020892,"PRICE LOSS COVERAGE PROGRAM":2747137.87,"NON-INSURED ASSISTANCE PROGRAM":61219}},{"year":2020,"amount":1278503.9000000001,"payments":95,"programs":{"TMP/MFP 2019 NON SPECIALTY CROPS":155153.5,"AGRICULTURAL RISK COVERAGE PROG - COUNTY":6088,"PRICE LOSS COVERAGE PROGRAM":553204,"CFAPCARES":241234.13,"CFAPCCA2":227049.65,"CFAPCCCCA":95774.62}}],"topPrograms":[{"program":"MARKET FACILITATION PROGRAM - CROPS","amount":5733230},{"program":"PRICE LOSS COVERAGE PROGRAM","amount":3387584.87},{"program":"AGRICULTURAL RISK COVERAGE PROG - COUNTY","amount":709474},{"program":"CFAPCARES","amount":241234.13},{"program":"CFAPCCA2","amount":227049.65},{"program":"TMP/MFP 2019 NON SPECIALTY CROPS","amount":155153.5},{"program":"CFAPCCCCA","amount":95774.62},{"program":"NON-INSURED ASSISTANCE PROGRAM","amount":61219}]}