{"slug":"bendickson-farms-general-partnership-garrison-nd","name":"BENDICKSON FARMS GENERAL PARTNERSHIP","state":"ND","city":"GARRISON","totalAmount":2459520.28,"totalPayments":11,"yearly":[],"topPrograms":[{"program":"EMGNCY RELIEF PRGM-NONSPECIALITY CROPS","amount":1132770},{"program":"EMERGENCY COMMODITY ASSISTANCE PROGRAM","amount":605799.12},{"program":"CFAP3 - TUP","amount":446761},{"program":"WHIP PLUS 3 ASSISTANCE","amount":271282},{"program":"SUPP DISASTER RELIEF NON-SPEC CROPS 1","amount":2908.16}]}