{"slug":"camrose-colony-inc-ledger-mt","name":"CAMROSE COLONY INC","state":"MT","city":"LEDGER","totalAmount":2228160.56,"totalPayments":121,"yearly":[],"topPrograms":[{"program":"CFAPCCA2","amount":329263},{"program":"EMGNCY RELIEF PRGM-NONSPECIALITY CROPS","amount":250000},{"program":"DAIRY MARGIN COVERAGE","amount":247566.94},{"program":"EMERGENCY COMMODITY ASSISTANCE PROGRAM","amount":218024.74},{"program":"PRICE LOSS COVERAGE PROGRAM","amount":206350},{"program":"SUPP DISASTER RELIEF NON-SPEC CROPS 1","amount":172647.26},{"program":"CFAP3 - TUP","amount":164752.4},{"program":"CFAPCCCCA","amount":132994.55},{"program":"AGRICULTURAL RISK COVERAGE PROG - COUNTY","amount":122016},{"program":"EMGNCY RELIEF PROGRAM-SPECIALITY CROPS","amount":104901.65},{"program":"SUPP DISASTER RELIEF SPEC CROPS 1","amount":84041.6},{"program":"CFAPCARES","amount":63471},{"program":"MARKETING ASSISTANCE FOR SPECIALTY CROPS","amount":44598.04},{"program":"LIVESTOCK FORAGE PROGRAM","amount":25586},{"program":"TMP/MFP 2019 LIVESTOCK","amount":15686.8}]}