{"slug":"cedar-ridge-dairy-llc-twin-falls-id","name":"CEDAR RIDGE DAIRY LLC","state":"ID","city":"TWIN FALLS","totalAmount":3295650.6,"totalPayments":13,"yearly":[],"topPrograms":[{"program":"EMERG ASSIST LIVESTOCK BEES FISH (ELAP)","amount":1623590.26},{"program":"CFAPCCA2","amount":750000},{"program":"CFAPCCCCA","amount":749950},{"program":"EMERGENCY COMMODITY ASSISTANCE PROGRAM","amount":108252.81},{"program":"PRICE LOSS COVERAGE PROGRAM","amount":55444},{"program":"TMP/MFP 2019 NON SPECIALTY CROPS","amount":8363.53},{"program":"CFAPCARES","amount":50}]}