{"slug":"dionisio-produce-and-farms-llc-pueblo-co","name":"DIONISIO PRODUCE AND FARMS LLC","state":"CO","city":"PUEBLO","totalAmount":3249040.91,"totalPayments":20,"yearly":[{"year":2021,"amount":701776.3300000001,"payments":7,"programs":{"CFAP3 - TUP":1183.2,"CFAPCCA2":24839.13,"NAP REGULAR WEB-BASED":282900,"WHIP PLUS 3 ASSISTANCE":392854}},{"year":2022,"amount":1507896.75,"payments":6,"programs":{"EMGNCY RELIEF PROGRAM-SPECIALITY CROPS":1224996.75,"NAP REGULAR WEB-BASED":282900}},{"year":2024,"amount":268736,"payments":2,"programs":{"NAP REGULAR WEB-BASED":267149,"AGRICULTURAL RISK COVERAGE PROG - COUNTY":1587}},{"year":2025,"amount":770631.83,"payments":5,"programs":{"NAP REGULAR WEB-BASED":260632,"SUPP DISASTER RELIEF SPEC CROPS 1":409428.6,"MARKETING ASSISTANCE FOR SPECIALTY CROPS":100571.23}}],"topPrograms":[{"program":"EMGNCY RELIEF PROGRAM-SPECIALITY CROPS","amount":1224996.75},{"program":"NAP REGULAR WEB-BASED","amount":1093581},{"program":"SUPP DISASTER RELIEF SPEC CROPS 1","amount":409428.6},{"program":"WHIP PLUS 3 ASSISTANCE","amount":392854},{"program":"MARKETING ASSISTANCE FOR SPECIALTY CROPS","amount":100571.23},{"program":"CFAPCCA2","amount":24839.13},{"program":"AGRICULTURAL RISK COVERAGE PROG - COUNTY","amount":1587},{"program":"CFAP3 - TUP","amount":1183.2}]}