{"slug":"doll-partnership-ingalls-ks","name":"DOLL PARTNERSHIP","state":"KS","city":"INGALLS","totalAmount":2737426.2,"totalPayments":96,"yearly":[],"topPrograms":[{"program":"PRICE LOSS COVERAGE PROGRAM","amount":643343.33},{"program":"CFAPCARES","amount":352024.8},{"program":"TMP/MFP 2019 NON SPECIALTY CROPS","amount":342649.68},{"program":"SUPP DISASTER RELIEF NON-SPEC CROPS 1","amount":307870.16},{"program":"EMGNCY RELIEF PRGM-NONSPECIALITY CROPS","amount":276368.27},{"program":"EMERGENCY COMMODITY ASSISTANCE PROGRAM","amount":271136.62},{"program":"CFAPCCCCA","amount":247975.2},{"program":"MARKET FACILITATION PROGRAM - CROPS","amount":127961},{"program":"CFAPCCA2","amount":66322.47},{"program":"CRP PAYMENT - ANNUAL RENTAL","amount":57369},{"program":"AGRICULTURAL RISK COVERAGE PROG - COUNTY","amount":21945},{"program":"CRP COST-SHARE WEB-BASED - COF","amount":8579},{"program":"WHIP PLUS 3 ASSISTANCE","amount":6976},{"program":"CRP - CONTINUOUS PIP","amount":6853},{"program":"ARC PROGRAM-COUNTY COVERAGE","amount":52}]}