{"slug":"farm-service-agency-commodity-credit-corporation-crowley-la","name":"FARM SERVICE AGENCY/COMMODITY CREDIT CORPORATION","state":"LA","city":"CROWLEY","totalAmount":2033234.8599999996,"totalPayments":115,"yearly":[{"year":2022,"amount":677481,"payments":70,"programs":{"PRICE LOSS COVERAGE":49798,"LIVESTOCK FORAGE PROGRAM":539861,"EMGNCY RELIEF PRGM-NONSPECIALITY CROPS":74364,"LIVESTOCK INDEMINITY PAYMENTS PROGRAM":13458}},{"year":2024,"amount":1355753.8599999996,"payments":45,"programs":{"AGRICULTURAL RISK COVERAGE PROG - COUNTY":12833,"EMERG ASSIST LIVESTOCK BEES FISH (ELAP)":1327527.1099999996,"LIVESTOCK FORAGE PROGRAM":9370,"EMGNCY RELIEF PRGM-NONSPECIALITY CROPS":3691.75,"CFAPCARES":1276,"CFAPCCCCA":1056}}],"topPrograms":[{"program":"EMERG ASSIST LIVESTOCK BEES FISH (ELAP)","amount":1327527.1099999996},{"program":"LIVESTOCK FORAGE PROGRAM","amount":549231},{"program":"EMGNCY RELIEF PRGM-NONSPECIALITY CROPS","amount":78055.75},{"program":"PRICE LOSS COVERAGE","amount":49798},{"program":"LIVESTOCK INDEMINITY PAYMENTS PROGRAM","amount":13458},{"program":"AGRICULTURAL RISK COVERAGE PROG - COUNTY","amount":12833},{"program":"CFAPCARES","amount":1276},{"program":"CFAPCCCCA","amount":1056}]}