{"slug":"first-state-bank-of-blakely-blakely-ga","name":"First State Bank of Blakely","state":"GA","city":"BLAKELY","totalAmount":11610955.94,"totalPayments":892,"yearly":[],"topPrograms":[{"program":"PRICE LOSS COVERAGE PROGRAM","amount":9775406.93},{"program":"AGRICULTURAL RISK COVERAGE PROG - COUNTY","amount":750715.5},{"program":"TMP/MFP 2019 NON SPECIALTY CROPS","amount":723833.83},{"program":"WILDFIRES AND HURRICANES INDEMNITY PROG","amount":171524},{"program":"DIS/WH2 2019 WFHURRINDEMP","amount":79941},{"program":"CFAPCCA2","amount":48360.27},{"program":"NON-INSURED ASSISTANCE PROGRAM","amount":28728},{"program":"CFAPCCCCA","amount":15311.6},{"program":"CFAPCARES","amount":13921.81},{"program":"TMP/MFP 2019 LIVESTOCK","amount":1650},{"program":"LIVESTOCK FORAGE PROGRAM","amount":1545},{"program":"AGRICULTURAL RISK COVERAGE -COUNTY PILOT","amount":18}]}