{"slug":"foster-brothers-partnership-lockney-tx","name":"FOSTER BROTHERS PARTNERSHIP","state":"TX","city":"LOCKNEY","totalAmount":4591290.909999999,"totalPayments":250,"yearly":[{"year":2018,"amount":244378,"payments":32,"programs":{"PRICE LOSS COVERAGE PROGRAM":159220,"COTTON GINNING COST SHARE PROGRAM":81780,"AGRICULTURAL RISK COVERAGE PROG - COUNTY":3378}},{"year":2019,"amount":1111800.32,"payments":71,"programs":{"PRICE LOSS COVERAGE PROGRAM":191284,"AGRICULTURAL RISK COVERAGE PROG - COUNTY":25145,"MARKET FACILITATION PROGRAM - CROPS":237924,"NON-INSURED ASSISTANCE PROGRAM":9654,"TMP/MFP 2019 NON SPECIALTY CROPS":647793.3200000001}},{"year":2020,"amount":749804.24,"payments":38,"programs":{"CFAPCCCCA":61050,"CFAPCCA2":269074.12,"CFAPCARES":4434,"TMP/MFP 2019 NON SPECIALTY CROPS":67087.12,"PRICE LOSS COVERAGE PROGRAM":338628,"LIVESTOCK FORAGE PROGRAM":9531}},{"year":2021,"amount":607655.2,"payments":47,"programs":{"PRICE LOSS COVERAGE PROGRAM":159192,"NON-INSURED ASSISTANCE PROGRAM":14039,"LIVESTOCK FORAGE PROGRAM":16389,"CFAP3 - TUP":161332.52,"CFAP3 - LTU":41184.52,"WHIP PLUS 3 ASSISTANCE":209991,"QUALITY LOSS ADJUSTMENT PROGRAM":5527.16}},{"year":2022,"amount":1120563.56,"payments":14,"programs":{"LIVESTOCK FORAGE PROGRAM":86632,"EMGNCY RELIEF PRGM-NONSPECIALITY CROPS":861601.44,"EMERGENCY LIVESTOCK RELIEF PROGRAM":82682.12000000001,"WEB-BASED NAP":77316,"CRP PAYMENT - ANNUAL RENTAL":12332}},{"year":2023,"amount":518514.04,"payments":29,"programs":{"AGRICULTURAL RISK COVERAGE PROG - COUNTY":31644,"EMRGNCY RELIEF PRGM TRK 1-NONSPCLTY CRPS":190847.08000000002,"EMERGENCY LIVESTOCK RELIEF PROGRAM":16536.44,"EMERGENCY LIVESTOCK RELIEF PROGRAM - CAA":27454.52,"LIVESTOCK FORAGE PROGRAM":215561,"WEB-BASED NAP":11772,"NON-INSURED ASSISTANCE PROGRAM":24699}},{"year":2024,"amount":238575.55,"payments":19,"programs":{"EMRGNCY RELIEF PRGM TRK 1-NONSPCLTY CRPS":45,"EMRGNCY RELIEF PRGM TRK 2-NONSPCLTY CRPS":121349.43,"EMGNCY RELIEF PRGM-NONSPECIALITY CROPS":40208.04,"EMERGENCY LIVESTOCK RELIEF PROGRAM - CAA":2059.0800000000004,"NON-INSURED ASSISTANCE PROGRAM":31378,"CRP PAYMENT - ANNUAL RENTAL":43536}}],"topPrograms":[{"program":"EMGNCY RELIEF PRGM-NONSPECIALITY CROPS","amount":901809.48},{"program":"PRICE LOSS COVERAGE PROGRAM","amount":848324},{"program":"TMP/MFP 2019 NON SPECIALTY CROPS","amount":714880.4400000001},{"program":"LIVESTOCK FORAGE PROGRAM","amount":328113},{"program":"CFAPCCA2","amount":269074.12},{"program":"MARKET FACILITATION PROGRAM - CROPS","amount":237924},{"program":"WHIP PLUS 3 ASSISTANCE","amount":209991},{"program":"EMRGNCY RELIEF PRGM TRK 1-NONSPCLTY CRPS","amount":190892.08000000002},{"program":"CFAP3 - TUP","amount":161332.52},{"program":"EMRGNCY RELIEF PRGM TRK 2-NONSPCLTY CRPS","amount":121349.43}]}