{"slug":"frey-farms-partnership-eunice-la","name":"FREY FARMS PARTNERSHIP","state":"LA","city":"EUNICE","totalAmount":1127937.47,"totalPayments":120,"yearly":[],"topPrograms":[{"program":"PRICE LOSS COVERAGE PROGRAM","amount":601080},{"program":"EMERG ASSIST LIVESTOCK BEES FISH (ELAP)","amount":177906.15},{"program":"TMP/MFP 2019 NON SPECIALTY CROPS","amount":98088.32},{"program":"WHIP PLUS 3 ASSISTANCE","amount":76126},{"program":"CFAPCARES","amount":54002.2},{"program":"CFAPCCA2","amount":47995.76},{"program":"MARKET FACILITATION PROGRAM - CROPS","amount":36512},{"program":"AGRICULTURAL RISK COVERAGE PROG - COUNTY","amount":29624},{"program":"CFAPCCCCA","amount":4482.28},{"program":"EMGNCY RELIEF PRGM-NONSPECIALITY CROPS","amount":2120.76}]}