{"slug":"hilmar-holsteins-inc-hilmar-ca","name":"HILMAR HOLSTEINS INC","state":"CA","city":"HILMAR","totalAmount":2419858.62,"totalPayments":8,"yearly":[{"year":2020,"amount":1364512.0799999998,"payments":6,"programs":{"CFAPCCCCA":253364.2,"CFAPCCA2":584202.22,"CFAPCARES":496635.8,"TMP/MFP 2019 LIVESTOCK":30309.86}},{"year":2025,"amount":1055346.54,"payments":2,"programs":{"EMERG ASSIST LIVESTOCK BEES FISH (ELAP)":1055346.54}}],"topPrograms":[{"program":"EMERG ASSIST LIVESTOCK BEES FISH (ELAP)","amount":1055346.54},{"program":"CFAPCCA2","amount":584202.22},{"program":"CFAPCARES","amount":496635.8},{"program":"CFAPCCCCA","amount":253364.2},{"program":"TMP/MFP 2019 LIVESTOCK","amount":30309.86}]}