{"slug":"jax-dairy-farms-inc-adams-mn","name":"JAX DAIRY FARMS INC","state":"MN","city":"ADAMS","totalAmount":1144265.54,"totalPayments":24,"yearly":[],"topPrograms":[{"program":"CFAPCARES","amount":434430.18},{"program":"CFAPCCA2","amount":430422.24},{"program":"CFAPCCCCA","amount":175936.51},{"program":"DAIRY MARGIN COVERAGE","amount":31562.71},{"program":"TMP/MFP 2019 NON SPECIALTY CROPS","amount":31217.24},{"program":"PRICE LOSS COVERAGE PROGRAM","amount":19915},{"program":"TMP/MFP 2019 LIVESTOCK","amount":15529.66},{"program":"AGRICULTURAL RISK COVERAGE PROG - COUNTY","amount":5252}]}