{"slug":"jordan-planters-partners-friendship-tn","name":"JORDAN PLANTERS PARTNERS","state":"TN","city":"FRIENDSHIP","totalAmount":2055625.3,"totalPayments":161,"yearly":[],"topPrograms":[{"program":"TMP/MFP 2019 NON SPECIALTY CROPS","amount":572667.55},{"program":"PRICE LOSS COVERAGE PROGRAM","amount":531870},{"program":"MARKET FACILITATION PROGRAM - CROPS","amount":351853},{"program":"CFAPCCA2","amount":179434.41},{"program":"CFAPCCCCA","amount":160061.74},{"program":"CFAPCARES","amount":144131.6},{"program":"COTTON GINNING COST SHARE PROGRAM","amount":103412},{"program":"AGRICULTURAL RISK COVERAGE PROG - COUNTY","amount":12195}]}