{"slug":"kurncz-farms-inc-saint-johns-mi","name":"KURNCZ FARMS INC","state":"MI","city":"SAINT JOHNS","totalAmount":1449547.92,"totalPayments":40,"yearly":[],"topPrograms":[{"program":"CFAPCCA2","amount":655310.15},{"program":"CFAPCARES","amount":517983.41},{"program":"CFAPCCCCA","amount":162089.92},{"program":"AGRICULTURAL RISK COVERAGE - INDIVIDUAL","amount":37689},{"program":"DAIRY MARGIN COVERAGE","amount":31562.71},{"program":"TMP/MFP 2019 LIVESTOCK","amount":18232.49},{"program":"TMP/MFP 2019 NON SPECIALTY CROPS","amount":18048.24},{"program":"PRICE LOSS COVERAGE PROGRAM","amount":5815},{"program":"AGRICULTURAL RISK COVERAGE PROG - COUNTY","amount":2817}]}