{"slug":"lbl-seider-farms-appleton-city-mo","name":"LBL SEIDER FARMS","state":"MO","city":"APPLETON CITY","totalAmount":1633817.61,"totalPayments":141,"yearly":[],"topPrograms":[{"program":"SUPP DISASTER RELIEF NON-SPEC CROPS 1","amount":385240.11},{"program":"MARKET FACILITATION PROGRAM - CROPS","amount":353344},{"program":"EMERGENCY COMMODITY ASSISTANCE PROGRAM","amount":236112.39},{"program":"PRICE LOSS COVERAGE PROGRAM","amount":165653},{"program":"WHIP PLUS 3 ASSISTANCE","amount":123730.01},{"program":"CFAPCCA2","amount":123244.5},{"program":"AGRICULTURAL RISK COVERAGE PROG - COUNTY","amount":98691},{"program":"TMP/MFP 2019 NON SPECIALTY CROPS","amount":61160.75},{"program":"CFAPCCCCA","amount":46516.56},{"program":"CFAPCARES","amount":40125.29}]}