{"slug":"meadowvale-dairy-llc-rock-valley-ia","name":"MEADOWVALE DAIRY LLC","state":"IA","city":"ROCK VALLEY","totalAmount":3316877.57,"totalPayments":22,"yearly":[],"topPrograms":[{"program":"EMERG ASSIST LIVESTOCK BEES FISH (ELAP)","amount":1894982.83},{"program":"CFAPCCA2","amount":500000},{"program":"CFAPCARES","amount":400000},{"program":"TMP/MFP 2019 LIVESTOCK","amount":250000},{"program":"MARKET FACILITATION PROGRAM - DAHG","amount":125000},{"program":"CFAPCCCCA","amount":100000},{"program":"DAIRY MARGIN COVERAGE PROGRAM","amount":25404.18},{"program":"TMP/MFP 2019 NON SPECIALTY CROPS","amount":20686.56},{"program":"MARKET FACILITATION PROGRAM - CROPS","amount":708},{"program":"AGRICULTURAL RISK COVERAGE PROG - COUNTY","amount":96}]}