{"slug":"murcrest-farms-llc-copenhagen-ny","name":"MURCREST FARMS LLC","state":"NY","city":"COPENHAGEN","totalAmount":1102041.46,"totalPayments":39,"yearly":[],"topPrograms":[{"program":"CFAPCARES","amount":400356.53},{"program":"CFAPCCA2","amount":357901.02},{"program":"CFAPCCCCA","amount":128853.29},{"program":"DAIRY MARGIN COVERAGE","amount":120507.55},{"program":"CFAP3 - TUP","amount":55802.18},{"program":"TMP/MFP 2019 NON SPECIALTY CROPS","amount":14951.5},{"program":"PRICE LOSS COVERAGE PROGRAM","amount":11795},{"program":"TMP/MFP 2019 LIVESTOCK","amount":10944.39},{"program":"AGRICULTURAL RISK COVERAGE PROG - COUNTY","amount":930}]}