{"slug":"naumes-inc-medford-or","name":"NAUMES INC","state":"OR","city":"MEDFORD","totalAmount":2911773.1500000004,"totalPayments":9,"yearly":[{"year":2020,"amount":1608781.6600000001,"payments":7,"programs":{"WHIP PLUS 3 ASSISTANCE":19058.01,"MARKET FACILITATION PROG-SPECIALTY CROPS":69497,"TMP/MFP 2019 SPECIALITY CROPS":63288.48,"CFAPCARES":706938.17,"CFAPCCA2":750000}},{"year":2022,"amount":1302991.49,"payments":2,"programs":{"EMGNCY RELIEF PROGRAM-SPECIALITY CROPS":1302991.49}}],"topPrograms":[{"program":"EMGNCY RELIEF PROGRAM-SPECIALITY CROPS","amount":1302991.49},{"program":"CFAPCCA2","amount":750000},{"program":"CFAPCARES","amount":706938.17},{"program":"MARKET FACILITATION PROG-SPECIALTY CROPS","amount":69497},{"program":"TMP/MFP 2019 SPECIALITY CROPS","amount":63288.48},{"program":"WHIP PLUS 3 ASSISTANCE","amount":19058.01}]}