{"slug":"ravi-and-jay-thiara-farms-yuba-city-ca","name":"RAVI AND JAY THIARA FARMS","state":"CA","city":"YUBA CITY","totalAmount":3432873.1999999997,"totalPayments":13,"yearly":[{"year":2020,"amount":981874.2799999999,"payments":4,"programs":{"CFAPCCA2":500000,"CFAPCARES":274876.94,"TMP/MFP 2019 SPECIALITY CROPS":206997.34}},{"year":2023,"amount":976747.25,"payments":2,"programs":{"PANDEMIC ASSISTANCE REVENUE PROGRAM":22012.79,"EMERGENCY RELIEF PRGM 2":954734.46}},{"year":2024,"amount":288495.85,"payments":3,"programs":{"PANDEMIC ASSISTANCE REVENUE PROGRAM":484.33,"EMGNCY RELIEF PROGRAM-SPECIALITY CROPS":12215.1,"EMRGNCY RELIEF PRGM TRACK 2-SPECLTY CRPS":275796.42}},{"year":2025,"amount":1185755.8199999998,"payments":4,"programs":{"SUPP DISASTER RELIEF SPEC CROPS 1":462044.36,"MARKETING ASSISTANCE FOR SPECIALTY CROPS":723711.46}}],"topPrograms":[{"program":"EMERGENCY RELIEF PRGM 2","amount":954734.46},{"program":"MARKETING ASSISTANCE FOR SPECIALTY CROPS","amount":723711.46},{"program":"CFAPCCA2","amount":500000},{"program":"SUPP DISASTER RELIEF SPEC CROPS 1","amount":462044.36},{"program":"EMRGNCY RELIEF PRGM TRACK 2-SPECLTY CRPS","amount":275796.42},{"program":"CFAPCARES","amount":274876.94},{"program":"TMP/MFP 2019 SPECIALITY CROPS","amount":206997.34},{"program":"PANDEMIC ASSISTANCE REVENUE PROGRAM","amount":22497.120000000003},{"program":"EMGNCY RELIEF PROGRAM-SPECIALITY CROPS","amount":12215.1}]}