{"slug":"root-brothers-albion-ny","name":"ROOT BROTHERS","state":"NY","city":"ALBION","totalAmount":2413378.88,"totalPayments":43,"yearly":[{"year":2017,"amount":198043,"payments":10,"programs":{"AGRICULTURAL RISK COVERAGE PROG - COUNTY":166897,"NON-INSURED ASSISTANCE PROGRAM":31146}},{"year":2019,"amount":392128.36,"payments":4,"programs":{"NON-INSURED ASSISTANCE PROGRAM":170295,"MARKET FACILITATION PROGRAM - CROPS":115606,"TMP/MFP 2019 NON SPECIALTY CROPS":106227.36000000002}},{"year":2020,"amount":718542.66,"payments":23,"programs":{"NON-INSURED ASSISTANCE PROGRAM":15728,"WHIP PLUS 3 ASSISTANCE":33781.5,"AGRICULTURAL RISK COVERAGE - INDIVIDUAL":7757,"TMP/MFP 2019 NON SPECIALTY CROPS":35409.12,"PRICE LOSS COVERAGE PROGRAM":34732,"CFAPCCA2":398381.28,"CFAPCCCCA":56548.2,"CFAPCARES":136205.56}},{"year":2022,"amount":576333.76,"payments":1,"programs":{"EMGNCY RELIEF PROGRAM-SPECIALITY CROPS":576333.76}},{"year":2025,"amount":528331.1,"payments":5,"programs":{"MARKETING ASSISTANCE FOR SPECIALTY CROPS":378874.14,"NON-INSURED ASSISTANCE PROGRAM":42167,"EMERGENCY COMMODITY ASSISTANCE PROGRAM":107289.95999999999}}],"topPrograms":[{"program":"EMGNCY RELIEF PROGRAM-SPECIALITY CROPS","amount":576333.76},{"program":"CFAPCCA2","amount":398381.28},{"program":"MARKETING ASSISTANCE FOR SPECIALTY CROPS","amount":378874.14},{"program":"NON-INSURED ASSISTANCE PROGRAM","amount":259336},{"program":"AGRICULTURAL RISK COVERAGE PROG - COUNTY","amount":166897},{"program":"TMP/MFP 2019 NON SPECIALTY CROPS","amount":141636.48},{"program":"CFAPCARES","amount":136205.56},{"program":"MARKET FACILITATION PROGRAM - CROPS","amount":115606},{"program":"EMERGENCY COMMODITY ASSISTANCE PROGRAM","amount":107289.95999999999},{"program":"CFAPCCCCA","amount":56548.2}]}