{"slug":"s-s-farms-harrold-sd","name":"S & S FARMS","state":"SD","city":"HARROLD","totalAmount":2034215.66,"totalPayments":123,"yearly":[],"topPrograms":[{"program":"EMGNCY RELIEF PRGM-NONSPECIALITY CROPS","amount":475058.16},{"program":"EMERGENCY COMMODITY ASSISTANCE PROGRAM","amount":271449.06},{"program":"PRICE LOSS COVERAGE PROGRAM","amount":269793},{"program":"AGRICULTURAL RISK COVERAGE PROG - COUNTY","amount":242602},{"program":"CRP PAYMENT - ANNUAL RENTAL","amount":170824},{"program":"TMP/MFP 2019 NON SPECIALTY CROPS","amount":147873.62},{"program":"CFAPCCA2","amount":141659.96},{"program":"SUPP DISASTER RELIEF NON-SPEC CROPS 1","amount":85116.54},{"program":"MARKET FACILITATION PROGRAM - CROPS","amount":72000},{"program":"EMGNCY RELIEF PROGRAM-SPECIALITY CROPS","amount":42884.36},{"program":"CFAPCCCCA","amount":40634.58},{"program":"CFAPCARES","amount":37533.58},{"program":"MARKETING ASSISTANCE FOR SPECIALTY CROPS","amount":21286.74},{"program":"SUPP DISASTER RELIEF SPEC CROPS 1","amount":6126.06},{"program":"AGRICULTURAL RISK COVERAGE - INDIVIDUAL","amount":4362}]}