{"slug":"sandrock-family-farms-rock-falls-il","name":"SANDROCK FAMILY FARMS","state":"IL","city":"ROCK FALLS","totalAmount":1107284.1,"totalPayments":81,"yearly":[],"topPrograms":[{"program":"CFAPCCA2","amount":226165.12},{"program":"AGRICULTURAL RISK COVERAGE PROG - COUNTY","amount":195142},{"program":"WHIP PLUS 3 ASSISTANCE","amount":167745},{"program":"MARKET FACILITATION PROGRAM - CROPS","amount":162956},{"program":"CFAP3 - TUP","amount":103184.8},{"program":"PRICE LOSS COVERAGE PROGRAM","amount":69739},{"program":"TMP/MFP 2019 NON SPECIALTY CROPS","amount":57970.66},{"program":"CFAPCCCCA","amount":46851.36},{"program":"CFAPCARES","amount":42741.16},{"program":"AGRICULTURAL RISK COVERAGE - INDIVIDUAL","amount":34289},{"program":"CCC ORGANIC COST SHARE - CROPS","amount":500}]}