{"slug":"state-line-farms-lyons-oh","name":"STATE LINE FARMS","state":"OH","city":"LYONS","totalAmount":2307299.6,"totalPayments":83,"yearly":[{"year":2017,"amount":190294,"payments":15,"programs":{"AGRICULTURAL RISK COVERAGE PROG - COUNTY":188635,"PRICE LOSS COVERAGE PROGRAM":135,"CRP PAYMENT - ANNUAL RENTAL":1524}},{"year":2018,"amount":386297,"payments":17,"programs":{"AGRICULTURAL RISK COVERAGE PROG - COUNTY":10715,"PRICE LOSS COVERAGE PROGRAM":134,"CRP PAYMENT - ANNUAL RENTAL":448,"MARKET FACILITATION PROGRAM - CROPS":375000}},{"year":2019,"amount":495866.95,"payments":12,"programs":{"PRICE LOSS COVERAGE PROGRAM":142,"AGRICULTURAL RISK COVERAGE PROG - COUNTY":935,"CRP PAYMENT - ANNUAL RENTAL":448,"TMP/MFP 2019 NON SPECIALTY CROPS":494341.95}},{"year":2020,"amount":829405.73,"payments":27,"programs":{"PRICE LOSS COVERAGE PROGRAM":80028,"AGRICULTURAL RISK COVERAGE PROG - COUNTY":954,"TMP/MFP 2019 NON SPECIALTY CROPS":93853.85,"AGRICULTURAL RISK COVERAGE - INDIVIDUAL":52918,"CFAPCARES":75538.87,"CFAPCCA2":442177.65,"CFAPCCCCA":83487.36,"CRP PAYMENT - ANNUAL RENTAL":448}},{"year":2025,"amount":405435.92,"payments":12,"programs":{"AGRICULTURAL RISK COVERAGE PROG - COUNTY":33000,"EMERGENCY COMMODITY ASSISTANCE PROGRAM":372435.92}}],"topPrograms":[{"program":"TMP/MFP 2019 NON SPECIALTY CROPS","amount":588195.8},{"program":"CFAPCCA2","amount":442177.65},{"program":"MARKET FACILITATION PROGRAM - CROPS","amount":375000},{"program":"EMERGENCY COMMODITY ASSISTANCE PROGRAM","amount":372435.92},{"program":"AGRICULTURAL RISK COVERAGE PROG - COUNTY","amount":234239},{"program":"CFAPCCCCA","amount":83487.36},{"program":"PRICE LOSS COVERAGE PROGRAM","amount":80439},{"program":"CFAPCARES","amount":75538.87},{"program":"AGRICULTURAL RISK COVERAGE - INDIVIDUAL","amount":52918},{"program":"CRP PAYMENT - ANNUAL RENTAL","amount":2868}]}