{"slug":"t-a-farms-helena-ar","name":"T & A FARMS","state":"AR","city":"HELENA","totalAmount":1122209.89,"totalPayments":40,"yearly":[],"topPrograms":[{"program":"TMP/MFP 2019 NON SPECIALTY CROPS","amount":512095.92},{"program":"PRICE LOSS COVERAGE PROGRAM","amount":285118},{"program":"CFAP3 - TUP","amount":170446.04},{"program":"QUALITY LOSS ADJUSTMENT PROGRAM","amount":86283.93},{"program":"MARKET FACILITATION PROGRAM - CROPS","amount":67713},{"program":"AGRICULTURAL RISK COVERAGE PROG - COUNTY","amount":553}]}