{"slug":"tyson-farms-partnership-denmark-tn","name":"TYSON FARMS PARTNERSHIP","state":"TN","city":"DENMARK","totalAmount":3724188.43,"totalPayments":672,"yearly":[],"topPrograms":[{"program":"TMP/MFP 2019 NON SPECIALTY CROPS","amount":833641.57},{"program":"PRICE LOSS COVERAGE PROGRAM","amount":620037},{"program":"EMERGENCY COMMODITY ASSISTANCE PROGRAM","amount":413042.58},{"program":"MARKET FACILITATION PROGRAM - CROPS","amount":375000},{"program":"EMRGNCY RELIEF PRGM TRK 2-NONSPCLTY CRPS","amount":290090.67},{"program":"SUPP DISASTER RELIEF NON-SPEC CROPS 1","amount":268589.71},{"program":"CFAPCCA2","amount":196658.9},{"program":"PRICE LOSS COVERAGE","amount":163512},{"program":"CFAP3 - TUP","amount":155881.4},{"program":"CFAPCCCCA","amount":105744.14},{"program":"WHIP PLUS 3 ASSISTANCE","amount":101894},{"program":"AGRICULTURAL RISK COVERAGE PROG - COUNTY","amount":99561},{"program":"CFAPCARES","amount":95784.33},{"program":"EMGNCY RELIEF PRGM-NONSPECIALITY CROPS","amount":4751.13}]}